reasoning_symbolic_regressor/__init__.py
reasoning_symbolic_regressor/regressor.py
reasoning_symbolic_regressor-0.1.0.dist-info/LICENSE
reasoning_symbolic_regressor-0.1.0.dist-info/METADATA
reasoning_symbolic_regressor-0.1.0.dist-info/WHEEL
reasoning_symbolic_regressor-0.1.0.dist-info/top_level.txt
reasoning_symbolic_regressor-0.1.0.dist-info/RECORD
