Metadata-Version: 2.2
Name: reasoning-symbolic-regressor
Version: 0.1.0
Summary: LLM-enhanced symbolic regression: A reasoning-driven AI that refines equations using structured feedback and adaptive learning.
Home-page: https://github.com/sidu/ReasoningSymbolicRegressor
Author: Sid Uppal
Author-email: siddhu@gmail.com
Classifier: Programming Language :: Python :: 3
Classifier: License :: OSI Approved :: MIT License
Classifier: Operating System :: OS Independent
Requires-Python: >=3.7
License-File: LICENSE
Requires-Dist: pysr
Requires-Dist: numpy
Requires-Dist: openai
Requires-Dist: pydantic
Dynamic: author
Dynamic: author-email
Dynamic: classifier
Dynamic: description
Dynamic: description-content-type
Dynamic: home-page
Dynamic: requires-dist
Dynamic: requires-python
Dynamic: summary
